desimpy-0.48.0.dist-info/METADATA
desimpy-0.48.0.dist-info/WHEEL
desimpy-0.48.0.dist-info/entry_points.txt
desimpy-0.48.0.dist-info/licenses/LICENSE
desimpy/.ruff_cache/.gitignore
desimpy/.ruff_cache/0.7.0/11453535399813473714
desimpy/.ruff_cache/CACHEDIR.TAG
desimpy/__init__.py
desimpy-0.48.0.dist-info/RECORD
