Metadata-Version: 2.1
Name: DESimpy
Version: 0.48.0
Summary: Discrete event simulation in using synchronous Python.
Author-Email: galenseilis <galen.seilis@seilis.ca>
License: Apache 2.0
Requires-Python: >=3.7
Requires-Dist: simdist>=0.1.1
